Design.v
`timescale 1ns / 1ps
//////////////////////////////////////////////////////////////////////////////////
// Company: 
// Engineer: 
// 
// Create Date: 20.04.2026 18:00:48
// Design Name: 
// Module Name: Dff
// Project Name: 
// Target Devices: 
// Tool Versions: 
// Description: 
// 
// Dependencies: 
// 
// Revision:
// Revision 0.01 - File Created
// Additional Comments:
// 
//////////////////////////////////////////////////////////////////////////////////


module Dff(
   input D_i, 
   input clk_i, 
   output reg Q_o, 
   output Qbar_o
);

assign Qbar_o = ~Q_o;
always@(posedge clk_i)
   Q_o <= D_i;

endmodule

Testbench.v
`timescale 1ns / 1ps
//////////////////////////////////////////////////////////////////////////////////
// Company: 
// Engineer: 
// 
// Create Date: 20.04.2026 18:01:16
// Design Name: 
// Module Name: tb_Dff
// Project Name: 
// Target Devices: 
// Tool Versions: 
// Description: 
// 
// Dependencies: 
// 
// Revision:
// Revision 0.01 - File Created
// Additional Comments:
// 
//////////////////////////////////////////////////////////////////////////////////


module tb_Dff();
reg D_ti; 
reg clk_ti;
wire Q_to; 
wire Qbar_to;

//net(s)
integer count;
integer pass;
integer fail;
reg exp_Q;
reg exp_Qbar;
reg D_pre;

//instantiation
Dff UUT(.D_i(D_ti), 
   .clk_i(clk_ti), 
   .Q_o(Q_to), 
   .Qbar_o(Qbar_to));

//initialization
initial begin
count = 0;
pass = 0;
fail = 0;
end

//capture
initial begin
$monitor("Time: %0t | D: %b, Clock: %b | Q: %b, Qn: %b", $time, D_ti, clk_ti, Q_to, Qbar_to);
$dumpfile("Dff.vcd");
$dumpvars(0, tb_Dff);
end

//clock
initial begin
   clk_ti = 1'b0;
   repeat(20)
      #5 clk_ti = ~clk_ti;
end

//feeding 
initial begin
   D_ti = 1'b0;      //t=0, low clk
   #1 check;
   #4 D_ti = 1'b1;   //5, rising clk
   #1 check;
   #2 D_ti = 1'b0;   //8, high clk
   #1 check;
   #5 D_ti = 1'b1;   //14, low clk
   #1 check; 
      D_ti = 1'b0;   //15, rising clk
   #1 check;
   #2 D_ti = 1'b1;   //18, high clk
   #1 check;
   #1 D_ti = 1'b0;   //20, falling clk
   #1 check;
   #9 D_ti = 1'b1;   //30, falling clk
   #1 check;
   #2 $display("Checks: %d, | Pass: %d, Fail: %d", count, pass, fail);
   #7 $finish;
end //checks may be syncronized after each posedge, clean code

always@(posedge clk_ti)
   D_pre <= D_ti; 
   
//self check -- may include bug for new design, i'll fix later: initialize check;, make it for posedge clk;
task check(); begin
exp_Q = D_pre;
exp_Qbar = ~D_pre;
if((exp_Q !== Q_to) || (exp_Qbar !== Qbar_to)) begin
   $display("Error | Time: %0t | D: %b, Clock: %b | Q: %b, Qn: %b | Exp Q: %b, Qn: %b", $time, D_ti, clk_ti, Q_to, Qbar_to, exp_Q, exp_Qbar);
   fail = fail + 1;
end
else
   pass = pass + 1;
count = count + 1;
end
endtask

endmodule

Dff.vcd
$date
   Mon Apr 20 21:05:02 2026
$end

$version
  2025.2
  $dumpfile ("Dff.vcd") 
$end

$timescale
  1ps
$end

$scope module tb_Dff $end
$var reg 1 ! D_ti $end
$var reg 1 " clk_ti $end
$var wire 1 # Q_to $end
$var wire 1 $ Qbar_to $end
$var integer 32 % count [31:0] $end
$var integer 32 & pass [31:0] $end
$var integer 32 ' fail [31:0] $end
$var reg 1 ( exp_Q $end
$var reg 1 ) exp_Qbar $end
$var reg 1 * D_pre $end
$scope module UUT $end
$var wire 1 + D_i $end
$var wire 1 , clk_i $end
$var reg 1 - Q_o $end
$var wire 1 $ Qbar_o $end
$upscope $end
$scope task check $end
$upscope $end
$upscope $end
$enddefinitions $end

#0
$dumpvars
0!
0"
x#
x$
b0 %
b0 &
b0 '
x(
x)
x*
0+
0,
x-
$end

#1000
b1 %
b1 &

#5000
1!
1"
1#
0$
1*
1+
1,
1-

#6000
b10 %
b10 &
1(
0)

#8000
0!
0+

#9000
b11 %
b11 &

#10000
0"
0,

#14000
1!
1+

#15000
0!
1"
0#
1$
b100 %
b100 &
0*
0+
1,
0-

#16000
b101 %
b101 &
0(
1)

#18000
1!
1+

#19000
b110 %
b110 &

#20000
0!
0"
0+
0,

#21000
b111 %
b111 &

#25000
1"
1,

#30000
1!
0"
1+
0,

#31000
b1000 %
b1000 &

#35000
1"
1#
0$
1*
1,
1-
